CHANGES.txt
LICENSE.txt
README.txt
bootstrap.py
buildout.cfg
setup.py
src/getpaid/__init__.py
src/getpaid.emailcheckout.egg-info/PKG-INFO
src/getpaid.emailcheckout.egg-info/SOURCES.txt
src/getpaid.emailcheckout.egg-info/dependency_links.txt
src/getpaid.emailcheckout.egg-info/namespace_packages.txt
src/getpaid.emailcheckout.egg-info/not-zip-safe
src/getpaid.emailcheckout.egg-info/requires.txt
src/getpaid.emailcheckout.egg-info/top_level.txt
src/getpaid/emailcheckout/__init__.py
src/getpaid/emailcheckout/checkout.py
src/getpaid/emailcheckout/configure.zcml
src/getpaid/emailcheckout/interfaces.py
src/getpaid/emailcheckout/options.py
src/getpaid/emailcheckout/overrides.zcml
src/getpaid/emailcheckout/processor.py
src/getpaid/emailcheckout/locales/getpaid.emailcheckout.pot
src/getpaid/emailcheckout/locales/de/LC_MESSAGES/getpaid.emailcheckout.po