Metadata-Version: 1.0
Name: getpaid.emailcheckout
Version: 0.1
Summary: getpaid payment processor that sends order information to the shop owner
Home-page: http://code.google.com/p/getpaid
Author: Getpaid Community
Author-email: getpaid-dev@googlegroups.com
License: ZPL2.1
Platform: UNKNOWN
Classifier: Framework :: Zope2
Classifier: Framework :: Zope3
Classifier: Framework :: Plone
